scatac_fragment_tools/__init__.py
scatac_fragment_tools/_rust_scatac_fragment_tools.abi3.so
scatac_fragment_tools/cli/__init__.py
scatac_fragment_tools/cli/commands.py
scatac_fragment_tools/cli/main.py
scatac_fragment_tools/library/__init__.py
scatac_fragment_tools/library/bigwig/__init__.py
scatac_fragment_tools/library/bigwig/fragments_to_bigwig.py
scatac_fragment_tools/library/split/__init__.py
scatac_fragment_tools/library/split/split_fragments_by_cell_type.py
scatac_fragment_tools-0.1.5.dist-info/METADATA
scatac_fragment_tools-0.1.5.dist-info/WHEEL
scatac_fragment_tools-0.1.5.dist-info/entry_points.txt
scatac_fragment_tools-0.1.5.dist-info/licenses/LICENSE
scatac_fragment_tools-0.1.5.dist-info/RECORD
