Metadata-Version: 2.4
Name: scatac_fragment_tools
Version: 0.1.5
Classifier: Programming Language :: Rust
Classifier: Programming Language :: Python :: Implementation :: CPython
Classifier: Programming Language :: Python :: Implementation :: PyPy
Requires-Dist: numpy
Requires-Dist: polars>=1.32.0
Requires-Dist: pyarrow
Requires-Dist: numba
Requires-Dist: rich-argparse
Requires-Dist: joblib
Requires-Dist: mypy ; extra == 'development'
Requires-Dist: ruff ; extra == 'development'
Requires-Dist: pytest ; extra == 'development'
Requires-Dist: pybigtools>=0.2.4 ; extra == 'pybigtools'
Requires-Dist: pybigwig ; extra == 'pybigwig'
Provides-Extra: development
Provides-Extra: pybigtools
Provides-Extra: pybigwig
License-File: LICENSE
Summary: Tools for working with scATAC-seq fragment files.
Keywords: scATAC-seq,scATAC,fragment files
Requires-Python: >=3.10
Project-URL: changelog, https://raw.githubusercontent.com/aertslab/scatac_fragment_tools/CHANGELOG.md
Project-URL: documentation, https://aertslab.github.io/scatac_fragment_tools/
Project-URL: homepage, https://github.com/aertslab/scatac_fragment_tools/
Project-URL: repository, https://github.com/aertslab/scatac_fragment_tools/
